{
  "id": "RM/1533/48/2025",
  "datum": "2025-03-13",
  "organ": "Rada města Litovel",
  "actions": [
    "souhlasí"
  ],
  "subject": "s uspořádáním veřejnosti přístupné sportovní akce, tj. s prezentací vozidel značky\nROVER ve vyhrazeném prostoru na nám. Přemysla Otakara v Litovli, v prostoru u Morového sloupu,\ndne 21. 6. 2025 v době od 9.00 do 12.45 hod. Pořadatelem akce bude prezident Roverclubu c.z., který bude nést\nv plném rozsahu odpovědnost za bezpečnost a pořádek v průběhu celé akce.",
  "items": [],
  "tail": null,
  "references_out": [],
  "amounts": []
}