{
  "id": "RM/1350/44/2024",
  "datum": "2024-12-05",
  "organ": "Rada města Litovel",
  "actions": [
    "schvaluje"
  ],
  "subject": "uzavření Smlouvy o výpůjčce (číslo půjčitele 133/54/2024) mezi městem Litovel\n(Muzeum Litovel) na straně vypůjčitele a Vlastivědným muzeem v Olomouci na straně půjčitele, jejímž předmětem\nje bezplatné zapůjčení výstavních předmětů (seznam výstavních předmětů tvoří přílohu smlouvy), v předloženém\nznění.",
  "items": [],
  "tail": null,
  "references_out": [],
  "amounts": []
}