{
  "id": "RM/2024/67/2026",
  "datum": "2026-01-29",
  "organ": "Rada města Litovel",
  "actions": [
    "schvaluje",
    "souhlasí"
  ],
  "subject": null,
  "items": [
    {
      "label": "a",
      "text": "souhlasí s poskytnutím daru ve výši 2.500 Kč na organizační zajištění maškarního karnevalu pro děti MŠ,\nkterý se bude konat 15. února 2026 v Sokolovně v Unčovicích."
    },
    {
      "label": "b",
      "text": "schvaluje uzavření smlouvy o poskytnutí daru mezi městem Litovel a Ing. L. K. v předloženém znění\na rozpočtovou změnu týkající se tohoto daru."
    }
  ],
  "tail": null,
  "references_out": [],
  "amounts": [
    "2.500 Kč"
  ]
}