{
  "id": "RM/48/2/2022",
  "organ": "Rada města Litovel",
  "actions": [
    "souhlasí",
    "vyhovuje"
  ],
  "subject": null,
  "items": [
    {
      "label": "a",
      "text": "vyhovuje žádosti pana Petra Čamka, jednatele společnosti IN LIFE Morava s.r.o., na základě uzavřené Nájemní\nsmlouvy (SML/0153/2021/MH) bod II."
    },
    {
      "label": "b",
      "text": "souhlasí se schválením investičního záměru na pozemku parc.č. 479/21 v k.ú. Litovel, který je ve vlastnictví\nměsta Litovel dle přiložené žádosti."
    }
  ],
  "tail": null,
  "references_out": [],
  "amounts": []
}