{
  "id": "RM/478/15/2023",
  "datum": "2023-06-22",
  "organ": "Rada města Litovel",
  "actions": [
    "schvaluje"
  ],
  "subject": "v souladu se zveřejněným záměrem města dle usn. č. RM/269/10/2023 z 10. schůze\nRM ze dne 30. 3. 2023 tyto nájemní smlouvy",
  "items": [
    {
      "label": "a",
      "text": "SML/0148/2023/MH na pronájem části pozemku parc.č. 859/18, lesní pozemek, o výměře 30 m2, nájemci L. a L.\nH. z Litovle, za roční nájemné 545 Kč."
    },
    {
      "label": "b",
      "text": "SML/0149/2023/MH na pronájem části pozemku parc.č. 859/19, o výměře 65 m2, nájemci J. a A. P. z Litovle,\nza roční nájemné 1.180 Kč."
    },
    {
      "label": "c",
      "text": "SML/0150/2023/MH na pronájem části pozemku parc.č. 859/19, o výměře 15 m2 a části pozemku parc.č. 859/18,\nnájemci J. a J. H. z Litovle, o výměře 30 m2, za roční nájemné 817 Kč."
    },
    {
      "label": "d",
      "text": "SML/0151/2023/MH na pronájem části pozemku parc.č. 859/18, o výměře 30 m2, nájemci V. K. z Litovle,"
    }
  ],
  "tail": "za roční nájemné 545 Kč.\nNájem je sjednán na dobu určitou s účinností od 1. 7. 2023 do 30. 6. 2025. Pozemek parc.č. 859/19 a 859/18 jsou\nlesní pozemky, v k.ú. Litovel, lokalita Revúcká. Všichni nájemci musí předložit orgánu správy lesů (OŽP) žádost\no dočasné odnětí pronajímaných částí pozemků z plnění funkcí lesa v souladu s ust. § 16, odst. (1), zák. číslo\n289/1995Sb.",
  "references_out": [],
  "amounts": [
    "1.180 Kč",
    "545 Kč",
    "817 Kč"
  ]
}