{
  "id": "RM/978/34/2024",
  "organ": "Rada města Litovel",
  "actions": [
    "schvaluje"
  ],
  "subject": null,
  "items": [
    {
      "label": "a",
      "text": "schvaluje dle předložené písemné zprávy administrátora výběrového řízení (KM admin s.r.o.) výběr dodavatele\nveřejné zakázky „ZŠ JUNGMANNOVA - REKONSTRUKCE DRUŽIN A OBNOVA IT VYBAVENÍ\nV ODBORNÝCH PRACOVNÁCH“ – DODÁVKA ICT A DODÁVKA POMŮCEK; Část 2: Dodávka pomůcek,\na to dodavatele MULTIP Moravia s.r.o., IČO 16627971, Palackého 1135/27, 741 01 Nový Jičín."
    },
    {
      "label": "b",
      "text": "schvaluje uzavření předložené kupní smlouvy (ve lhůtě stanovené v zákoně č. 134/2016 Sb., o zadávání\nveřejných zakázek, ve znění pozdějších předpisů a v souladu s § 124 ZZVZ) mezi městem Litovel a vítězným\ndodavatelem MULTIP Moravia s.r.o., IČO 16627971, Palackého 1135/27, 741 01 Nový Jičín."
    }
  ],
  "tail": null,
  "references_out": [],
  "amounts": []
}