{
  "id": "ZM/8/19/2025",
  "datum": "2025-04-23",
  "organ": "Zastupitelstvo města Litovel",
  "actions": [
    "souhlasí"
  ],
  "subject": "s vyčleněním částky 500.000 Kč z veřejné sbírky města Litovle, kterou\nměsto Litovel zřídilo na popovodňovou pomoc (osvědčení KÚ č.j. KÚOK/109300/2024/OK/865 ze dne 19. 9.\n2024), a jejím použitím na pomoc občanům města Litovel, kteří byli postiženi povodní. O konkrétním rozdělení\nčástky formou daru rozhodne Rada města Litovel v rámci svých pravomocí.",
  "items": [],
  "tail": null,
  "references_out": [],
  "amounts": [
    "500.000 Kč"
  ]
}